caniusepython3/__init__.py
caniusepython3/__main__.py
caniusepython3/command.py
caniusepython3/dependencies.py
caniusepython3/overrides.json
caniusepython3/projects.py
caniusepython3/pylint_checker.py
caniusepython3/pypi.py
caniusepython3/test/__init__.py
caniusepython3/test/test_check.py
caniusepython3/test/test_cli.py
caniusepython3/test/test_command.py
caniusepython3/test/test_dependencies.py
caniusepython3/test/test_pylint_checker.py
caniusepython3/test/test_pypi.py
caniusepython3-7.2.0.dist-info/LICENSE
caniusepython3-7.2.0.dist-info/METADATA
caniusepython3-7.2.0.dist-info/WHEEL
caniusepython3-7.2.0.dist-info/entry_points.txt
caniusepython3-7.2.0.dist-info/top_level.txt
caniusepython3-7.2.0.dist-info/zip-safe
caniusepython3-7.2.0.dist-info/RECORD
